json_coder/__init__.py
json_coder-0.5.1.dist-info/LICENSE
json_coder-0.5.1.dist-info/METADATA
json_coder-0.5.1.dist-info/WHEEL
json_coder-0.5.1.dist-info/top_level.txt
json_coder-0.5.1.dist-info/RECORD
